cyanbot/__init__.py
cyanbot/__main__.py
cyanbot/context/__init__.py
cyanbot/instance/__init__.py
cyanbot/instance/manager.py
cyanbot/plugin/__init__.py
cyanbot/py.typed
cyanbot-0.1.1.dist-info/entry_points.txt
cyanbot-0.1.1.dist-info/WHEEL
cyanbot-0.1.1.dist-info/METADATA
cyanbot-0.1.1.dist-info/RECORD
